setup.cfg
setup.py
monolog/__init__.py
monolog/monolog.py
monolog/examples/__init__.py
monolog/examples/example.py
monolog_python.egg-info/PKG-INFO
monolog_python.egg-info/SOURCES.txt
monolog_python.egg-info/dependency_links.txt
monolog_python.egg-info/top_level.txt