Metadata-Version: 1.1
Name: monolog-python
Version: 0.1.0
Summary: Python's logging formatter compatible with https://github.com/macbre/monolog-utils
Home-page: https://github.com/macbre/monolog-python
Author: Maciej Brencz
Author-email: maciej.brencz@gmail.com
License: UNKNOWN
Keywords: logging json syslog monolog php
Platform: UNKNOWN
Classifier: Environment :: Console
Classifier: Programming Language :: Python :: 2
Classifier: Programming Language :: Python :: 2.7
Classifier: Programming Language :: Python :: 3
Classifier: Programming Language :: Python :: 3.3
Classifier: Programming Language :: Python :: 3.4
